isab/__init__.py
isab/isab.py
isab/test_isab.py
isab/version.py
isab-0.1.0.dist-info/LICENSE
isab-0.1.0.dist-info/METADATA
isab-0.1.0.dist-info/WHEEL
isab-0.1.0.dist-info/top_level.txt
isab-0.1.0.dist-info/RECORD
